manifest_checker/environment.py
manifest_checker/check.py
manifest_checker/__init__.py
manifest_checker/create.py
manifest_checker/main.py
manifest_checker/manifest
manifest_checker/defaults.py
manifest_checker/lib.py
manifest_checker-0.0.2rc6.dist-info/METADATA
manifest_checker-0.0.2rc6.dist-info/WHEEL
manifest_checker-0.0.2rc6.dist-info/RECORD
manifest_checker-0.0.2rc6.dist-info/entry_points.txt
manifest_checker-0.0.2rc6.dist-info/DESCRIPTION.rst
manifest_checker-0.0.2rc6.dist-info/metadata.json
manifest_checker-0.0.2rc6.dist-info/top_level.txt
