Metadata-Version: 2.0
Name: manifest-checker
Version: 0.0.2rc6
Summary: Simple to use tools to create and check directory contents - ideal for integrity checking
Home-page: http://manifest-checker.readthedocs.org/en/latest/
Author: Tony Flury
Author-email: anthony.flury@btinternet.com
License: GNU General Public License (GPL)
Keywords: Development,Deployment,Integrity Checking
Platform: UNKNOWN
Classifier: Development Status :: 4 - Beta
Classifier: Intended Audience :: Developers
Classifier: Framework :: Django
Classifier: Natural Language :: English
Classifier: Topic :: Software Development :: Quality Assurance
Classifier: License :: OSI Approved :: GNU General Public License (GPL)
Classifier: Programming Language :: Python :: 2.7
Requires-Dist: Click
Provides-Extra: dev
Requires-Dist: check-manifest; extra == 'dev'
Provides-Extra: test
Requires-Dist: coverage; extra == 'test'
